{
  "updatedAt": 1784734005,
  "source": "yahoo_finance",
  "settings": {
    "liquidityThreshold": 10000000,
    "breakoutWindow": 20,
    "breakoutPct": 0.02,
    "volumeSpikeMultiplier": 2.0
  },
  "items": [
    {
      "company": "SAP SE",
      "ticker": "SAP.DE",
      "symbol": "SAP.DE",
      "column": "software",
      "currentPrice": 132.1999969482422,
      "change": -4.22,
      "percentChange": -3.0934,
      "high": 136.39999389648438,
      "low": 132.05999755859375,
      "open": 136.02000427246094,
      "prevClose": 136.4199981689453,
      "volume": 1970450,
      "avgVolume20": 2303665,
      "avgDollarVolume20": 304544559,
      "liquid": true,
      "catalyst": true,
      "catalystHeadline": null,
      "breakout": false,
      "breakoutLevel": 143.89999389648438,
      "volumeSpike2x": false,
      "quoteTimestamp": "2026-07-22 00:00:00+02:00",
      "signal": "Hold",
      "dataSource": "Yahoo Finance / yfinance"
    },
    {
      "company": "Siemens AG",
      "ticker": "SIE.DE",
      "symbol": "SIE.DE",
      "column": "industrial",
      "currentPrice": 271.54998779296875,
      "change": 1.1,
      "percentChange": 0.4067,
      "high": 273.0,
      "low": 267.5,
      "open": 267.54998779296875,
      "prevClose": 270.45001220703125,
      "volume": 399400,
      "avgVolume20": 931720,
      "avgDollarVolume20": 253008555,
      "liquid": true,
      "catalyst": true,
      "catalystHeadline": null,
      "breakout": false,
      "breakoutLevel": 284.1000061035156,
      "volumeSpike2x": false,
      "quoteTimestamp": "2026-07-22 00:00:00+02:00",
      "signal": "Hold",
      "dataSource": "Yahoo Finance / yfinance"
    },
    {
      "company": "Deutsche Telekom AG",
      "ticker": "DTE.DE",
      "symbol": "DTE.DE",
      "column": "telecom",
      "currentPrice": 27.219999313354492,
      "change": 0.54,
      "percentChange": 2.024,
      "high": 27.270000457763672,
      "low": 26.579999923706055,
      "open": 26.889999389648438,
      "prevClose": 26.68000030517578,
      "volume": 3125825,
      "avgVolume20": 6492927,
      "avgDollarVolume20": 176737478,
      "liquid": true,
      "catalyst": true,
      "catalystHeadline": null,
      "breakout": false,
      "breakoutLevel": 27.110000610351562,
      "volumeSpike2x": false,
      "quoteTimestamp": "2026-07-22 00:00:00+02:00",
      "signal": "Hold",
      "dataSource": "Yahoo Finance / yfinance"
    },
    {
      "company": "Allianz SE",
      "ticker": "ALV.DE",
      "symbol": "ALV.DE",
      "column": "insurance",
      "currentPrice": 427.0,
      "change": 4.2,
      "percentChange": 0.9934,
      "high": 430.6000061035156,
      "low": 422.29998779296875,
      "open": 422.79998779296875,
      "prevClose": 422.79998779296875,
      "volume": 358535,
      "avgVolume20": 460254,
      "avgDollarVolume20": 196528522,
      "liquid": true,
      "catalyst": true,
      "catalystHeadline": null,
      "breakout": false,
      "breakoutLevel": 422.8999938964844,
      "volumeSpike2x": false,
      "quoteTimestamp": "2026-07-22 00:00:00+02:00",
      "signal": "Hold",
      "dataSource": "Yahoo Finance / yfinance"
    },
    {
      "company": "Deutsche Boerse AG",
      "ticker": "DB1.DE",
      "symbol": "DB1.DE",
      "column": "exchange",
      "currentPrice": 255.1999969482422,
      "change": 2.7,
      "percentChange": 1.0693,
      "high": 255.5,
      "low": 249.8000030517578,
      "open": 251.8000030517578,
      "prevClose": 252.5,
      "volume": 139285,
      "avgVolume20": 282133,
      "avgDollarVolume20": 72000366,
      "liquid": true,
      "catalyst": true,
      "catalystHeadline": null,
      "breakout": false,
      "breakoutLevel": 260.8999938964844,
      "volumeSpike2x": false,
      "quoteTimestamp": "2026-07-22 00:00:00+02:00",
      "signal": "Hold",
      "dataSource": "Yahoo Finance / yfinance"
    },
    {
      "company": "Mercedes-Benz Group AG",
      "ticker": "MBG.DE",
      "symbol": "MBG.DE",
      "column": "auto",
      "currentPrice": 44.94499969482422,
      "change": 0.04,
      "percentChange": 0.0891,
      "high": 45.19499969482422,
      "low": 44.439998626708984,
      "open": 44.724998474121094,
      "prevClose": 44.904998779296875,
      "volume": 695783,
      "avgVolume20": 2137685,
      "avgDollarVolume20": 96078252,
      "liquid": true,
      "catalyst": true,
      "catalystHeadline": null,
      "breakout": false,
      "breakoutLevel": 46.28499984741211,
      "volumeSpike2x": false,
      "quoteTimestamp": "2026-07-22 00:00:00+02:00",
      "signal": "Hold",
      "dataSource": "Yahoo Finance / yfinance"
    },
    {
      "company": "Volkswagen AG Pref",
      "ticker": "VOW3.DE",
      "symbol": "VOW3.DE",
      "column": "auto",
      "currentPrice": 73.12000274658203,
      "change": 0.56,
      "percentChange": 0.7718,
      "high": 73.63999938964844,
      "low": 71.68000030517578,
      "open": 72.12000274658203,
      "prevClose": 72.55999755859375,
      "volume": 300368,
      "avgVolume20": 1069497,
      "avgDollarVolume20": 78201609,
      "liquid": true,
      "catalyst": true,
      "catalystHeadline": null,
      "breakout": false,
      "breakoutLevel": 76.0199966430664,
      "volumeSpike2x": false,
      "quoteTimestamp": "2026-07-22 00:00:00+02:00",
      "signal": "Hold",
      "dataSource": "Yahoo Finance / yfinance"
    },
    {
      "company": "BMW AG Pref",
      "ticker": "BMW.DE",
      "symbol": "BMW.DE",
      "column": "auto",
      "currentPrice": 57.81999969482422,
      "change": 0.26,
      "percentChange": 0.4517,
      "high": 58.2599983215332,
      "low": 56.900001525878906,
      "open": 57.29999923706055,
      "prevClose": 57.560001373291016,
      "volume": 834660,
      "avgVolume20": 1519064,
      "avgDollarVolume20": 87832300,
      "liquid": true,
      "catalyst": true,
      "catalystHeadline": null,
      "breakout": false,
      "breakoutLevel": 60.900001525878906,
      "volumeSpike2x": false,
      "quoteTimestamp": "2026-07-22 00:00:00+02:00",
      "signal": "Hold",
      "dataSource": "Yahoo Finance / yfinance"
    },
    {
      "company": "Infineon Technologies AG",
      "ticker": "IFX.DE",
      "symbol": "IFX.DE",
      "column": "semiconductor",
      "currentPrice": 69.61000061035156,
      "change": 2.07,
      "percentChange": 3.0648,
      "high": 69.61000061035156,
      "low": 66.19000244140625,
      "open": 66.38999938964844,
      "prevClose": 67.54000091552734,
      "volume": 3323619,
      "avgVolume20": 4144091,
      "avgDollarVolume20": 288470160,
      "liquid": true,
      "catalyst": true,
      "catalystHeadline": null,
      "breakout": false,
      "breakoutLevel": 82.01000213623047,
      "volumeSpike2x": false,
      "quoteTimestamp": "2026-07-22 00:00:00+02:00",
      "signal": "Hold",
      "dataSource": "Yahoo Finance / yfinance"
    },
    {
      "company": "BASF SE",
      "ticker": "BAS.DE",
      "symbol": "BAS.DE",
      "column": "chemicals",
      "currentPrice": 48.96500015258789,
      "change": 0.72,
      "percentChange": 1.4924,
      "high": 49.33000183105469,
      "low": 48.0,
      "open": 48.04999923706055,
      "prevClose": 48.244998931884766,
      "volume": 842398,
      "avgVolume20": 1961202,
      "avgDollarVolume20": 96030242,
      "liquid": true,
      "catalyst": true,
      "catalystHeadline": null,
      "breakout": false,
      "breakoutLevel": 49.41999816894531,
      "volumeSpike2x": false,
      "quoteTimestamp": "2026-07-22 00:00:00+02:00",
      "signal": "Hold",
      "dataSource": "Yahoo Finance / yfinance"
    },
    {
      "company": "Bayer AG",
      "ticker": "BAYN.DE",
      "symbol": "BAYN.DE",
      "column": "healthcare",
      "currentPrice": 46.84000015258789,
      "change": -0.78,
      "percentChange": -1.638,
      "high": 47.86000061035156,
      "low": 46.630001068115234,
      "open": 47.86000061035156,
      "prevClose": 47.619998931884766,
      "volume": 820598,
      "avgVolume20": 3784786,
      "avgDollarVolume20": 177279391,
      "liquid": true,
      "catalyst": true,
      "catalystHeadline": null,
      "breakout": false,
      "breakoutLevel": 53.36000061035156,
      "volumeSpike2x": false,
      "quoteTimestamp": "2026-07-22 00:00:00+02:00",
      "signal": "Hold",
      "dataSource": "Yahoo Finance / yfinance"
    },
    {
      "company": "Rheinmetall AG",
      "ticker": "RHM.DE",
      "symbol": "RHM.DE",
      "column": "defense",
      "currentPrice": 1012.5999755859375,
      "change": 17.2,
      "percentChange": 1.7279,
      "high": 1023.2000122070312,
      "low": 993.2999877929688,
      "open": 1007.0,
      "prevClose": 995.4000244140625,
      "volume": 88482,
      "avgVolume20": 300677,
      "avgDollarVolume20": 304465168,
      "liquid": true,
      "catalyst": true,
      "catalystHeadline": null,
      "breakout": false,
      "breakoutLevel": 1130.0,
      "volumeSpike2x": false,
      "quoteTimestamp": "2026-07-22 00:00:00+02:00",
      "signal": "Hold",
      "dataSource": "Yahoo Finance / yfinance"
    },
    {
      "company": "Airbus SE",
      "ticker": "AIR.PA",
      "symbol": "AIR.PA",
      "column": "aerospace",
      "currentPrice": 207.60000610351562,
      "change": 13.0,
      "percentChange": 6.6804,
      "high": 209.0500030517578,
      "low": 202.5,
      "open": 202.5,
      "prevClose": 194.60000610351562,
      "volume": 1261149,
      "avgVolume20": 1015705,
      "avgDollarVolume20": 210860416,
      "liquid": true,
      "catalyst": true,
      "catalystHeadline": null,
      "breakout": false,
      "breakoutLevel": 209.39999389648438,
      "volumeSpike2x": false,
      "quoteTimestamp": "2026-07-22 00:00:00+02:00",
      "signal": "Hold",
      "dataSource": "Yahoo Finance / yfinance"
    },
    {
      "company": "ASML Holding N.V.",
      "ticker": "ASML.AS",
      "symbol": "ASML.AS",
      "column": "semiconductor",
      "currentPrice": 1584.199951171875,
      "change": -9.2001,
      "percentChange": -0.5774,
      "high": 1584.4000244140625,
      "low": 1537.5999755859375,
      "open": 1558.0,
      "prevClose": 1593.4000244140625,
      "volume": 439163,
      "avgVolume20": 665239,
      "avgDollarVolume20": 1053872225,
      "liquid": true,
      "catalyst": true,
      "catalystHeadline": null,
      "breakout": false,
      "breakoutLevel": 1721.4000244140625,
      "volumeSpike2x": false,
      "quoteTimestamp": "2026-07-22 00:00:00+02:00",
      "signal": "Hold",
      "dataSource": "Yahoo Finance / yfinance"
    },
    {
      "company": "BE Semiconductor Industries N.V.",
      "ticker": "BESI.AS",
      "symbol": "BESI.AS",
      "column": "semiconductor",
      "currentPrice": 248.1999969482422,
      "change": 8.7,
      "percentChange": 3.6326,
      "high": 248.39999389648438,
      "low": 235.1999969482422,
      "open": 237.3000030517578,
      "prevClose": 239.5,
      "volume": 315637,
      "avgVolume20": 387956,
      "avgDollarVolume20": 96290604,
      "liquid": true,
      "catalyst": true,
      "catalystHeadline": null,
      "breakout": false,
      "breakoutLevel": 292.8999938964844,
      "volumeSpike2x": false,
      "quoteTimestamp": "2026-07-22 00:00:00+02:00",
      "signal": "Hold",
      "dataSource": "Yahoo Finance / yfinance"
    },
    {
      "company": "STMicroelectronics N.V.",
      "ticker": "STMPA.PA",
      "symbol": "STMPA.PA",
      "column": "semiconductor",
      "currentPrice": 58.130001068115234,
      "change": 0.88,
      "percentChange": 1.5371,
      "high": 58.130001068115234,
      "low": 56.22999954223633,
      "open": 56.810001373291016,
      "prevClose": 57.25,
      "volume": 1245650,
      "avgVolume20": 2549898,
      "avgDollarVolume20": 148225582,
      "liquid": true,
      "catalyst": true,
      "catalystHeadline": null,
      "breakout": false,
      "breakoutLevel": 65.05999755859375,
      "volumeSpike2x": false,
      "quoteTimestamp": "2026-07-22 00:00:00+02:00",
      "signal": "Hold",
      "dataSource": "Yahoo Finance / yfinance"
    },
    {
      "company": "Dassault Systemes SE",
      "ticker": "DSY.PA",
      "symbol": "DSY.PA",
      "column": "software",
      "currentPrice": 17.8700008392334,
      "change": -0.045,
      "percentChange": -0.2512,
      "high": 18.075000762939453,
      "low": 17.55500030517578,
      "open": 17.94499969482422,
      "prevClose": 17.915000915527344,
      "volume": 793463,
      "avgVolume20": 1773205,
      "avgDollarVolume20": 31687182,
      "liquid": true,
      "catalyst": true,
      "catalystHeadline": null,
      "breakout": false,
      "breakoutLevel": 18.670000076293945,
      "volumeSpike2x": false,
      "quoteTimestamp": "2026-07-22 00:00:00+02:00",
      "signal": "Hold",
      "dataSource": "Yahoo Finance / yfinance"
    },
    {
      "company": "Schneider Electric SE",
      "ticker": "SU.PA",
      "symbol": "SU.PA",
      "column": "industrial",
      "currentPrice": 269.8999938964844,
      "change": 1.1,
      "percentChange": 0.4092,
      "high": 271.1000061035156,
      "low": 264.70001220703125,
      "open": 265.0,
      "prevClose": 268.79998779296875,
      "volume": 318072,
      "avgVolume20": 792627,
      "avgDollarVolume20": 213930117,
      "liquid": true,
      "catalyst": true,
      "catalystHeadline": null,
      "breakout": false,
      "breakoutLevel": 285.3999938964844,
      "volumeSpike2x": false,
      "quoteTimestamp": "2026-07-22 00:00:00+02:00",
      "signal": "Hold",
      "dataSource": "Yahoo Finance / yfinance"
    },
    {
      "company": "Safran SA",
      "ticker": "SAF.PA",
      "symbol": "SAF.PA",
      "column": "aerospace",
      "currentPrice": 326.5,
      "change": 3.6,
      "percentChange": 1.1149,
      "high": 328.20001220703125,
      "low": 322.6000061035156,
      "open": 323.29998779296875,
      "prevClose": 322.8999938964844,
      "volume": 259880,
      "avgVolume20": 631770,
      "avgDollarVolume20": 206272970,
      "liquid": true,
      "catalyst": true,
      "catalystHeadline": null,
      "breakout": false,
      "breakoutLevel": 357.1000061035156,
      "volumeSpike2x": false,
      "quoteTimestamp": "2026-07-22 00:00:00+02:00",
      "signal": "Hold",
      "dataSource": "Yahoo Finance / yfinance"
    },
    {
      "company": "Euronext N.V.",
      "ticker": "ENX.PA",
      "symbol": "ENX.PA",
      "column": "exchange",
      "currentPrice": 148.6999969482422,
      "change": 1.8,
      "percentChange": 1.2253,
      "high": 148.6999969482422,
      "low": 145.6999969482422,
      "open": 147.0,
      "prevClose": 146.89999389648438,
      "volume": 47148,
      "avgVolume20": 164201,
      "avgDollarVolume20": 24416673,
      "liquid": true,
      "catalyst": true,
      "catalystHeadline": null,
      "breakout": false,
      "breakoutLevel": 151.6999969482422,
      "volumeSpike2x": false,
      "quoteTimestamp": "2026-07-22 00:00:00+02:00",
      "signal": "Hold",
      "dataSource": "Yahoo Finance / yfinance"
    },
    {
      "company": "Rolls-Royce Holdings plc",
      "ticker": "RR.L",
      "symbol": "RR.L",
      "column": "aerospace",
      "currentPrice": 1397.800048828125,
      "change": 25.2001,
      "percentChange": 1.8359,
      "high": 1418.0,
      "low": 1376.4000244140625,
      "open": 1376.800048828125,
      "prevClose": 1372.5999755859375,
      "volume": 4744812,
      "avgVolume20": 19251138,
      "avgDollarVolume20": 26909241217,
      "liquid": true,
      "catalyst": true,
      "catalystHeadline": null,
      "breakout": false,
      "breakoutLevel": 1504.199951171875,
      "volumeSpike2x": false,
      "quoteTimestamp": "2026-07-22 00:00:00+01:00",
      "signal": "Hold",
      "dataSource": "Yahoo Finance / yfinance"
    },
    {
      "company": "BAE Systems plc",
      "ticker": "BA.L",
      "symbol": "BA.L",
      "column": "defense",
      "currentPrice": 1928.0,
      "change": 19.0,
      "percentChange": 0.9953,
      "high": 1939.5,
      "low": 1899.0,
      "open": 1903.5,
      "prevClose": 1909.0,
      "volume": 2217948,
      "avgVolume20": 6446324,
      "avgDollarVolume20": 12428512865,
      "liquid": true,
      "catalyst": true,
      "catalystHeadline": null,
      "breakout": false,
      "breakoutLevel": 2025.0,
      "volumeSpike2x": false,
      "quoteTimestamp": "2026-07-22 00:00:00+01:00",
      "signal": "Hold",
      "dataSource": "Yahoo Finance / yfinance"
    },
    {
      "company": "RELX PLC",
      "ticker": "REL.L",
      "symbol": "REL.L",
      "column": "information",
      "currentPrice": 2455.5,
      "change": 1.5,
      "percentChange": 0.0611,
      "high": 2512.0,
      "low": 2403.034912109375,
      "open": 2444.0,
      "prevClose": 2454.0,
      "volume": 1539922,
      "avgVolume20": 3895845,
      "avgDollarVolume20": 9566246293,
      "liquid": true,
      "catalyst": true,
      "catalystHeadline": null,
      "breakout": false,
      "breakoutLevel": 2518.0,
      "volumeSpike2x": false,
      "quoteTimestamp": "2026-07-22 00:00:00+01:00",
      "signal": "Hold",
      "dataSource": "Yahoo Finance / yfinance"
    },
    {
      "company": "ABB Ltd",
      "ticker": "ABBN.SW",
      "symbol": "ABBN.SW",
      "column": "industrial",
      "currentPrice": 80.86000061035156,
      "change": -0.02,
      "percentChange": -0.0247,
      "high": 81.31999969482422,
      "low": 79.44000244140625,
      "open": 80.44000244140625,
      "prevClose": 80.87999725341797,
      "volume": 1827332,
      "avgVolume20": 2589034,
      "avgDollarVolume20": 209349254,
      "liquid": true,
      "catalyst": true,
      "catalystHeadline": null,
      "breakout": false,
      "breakoutLevel": 87.58000183105469,
      "volumeSpike2x": false,
      "quoteTimestamp": "2026-07-22 00:00:00+02:00",
      "signal": "Hold",
      "dataSource": "Yahoo Finance / yfinance"
    }
  ],
  "errors": []
}