{
  "updatedAt": 1783264084,
  "source": "yahoo_finance",
  "settings": {
    "liquidityThreshold": 10000000,
    "breakoutWindow": 20,
    "breakoutPct": 0.02,
    "volumeSpikeMultiplier": 2.0
  },
  "items": [
    {
      "company": "SAP SE",
      "ticker": "SAP.DE",
      "symbol": "SAP.DE",
      "column": "software",
      "currentPrice": 139.63999938964844,
      "change": -2.08,
      "percentChange": -1.4677,
      "high": 141.9199981689453,
      "low": 138.6999969482422,
      "open": 141.5,
      "prevClose": 141.72000122070312,
      "volume": 1384012,
      "avgVolume20": 3055916,
      "avgDollarVolume20": 426728150,
      "liquid": true,
      "catalyst": true,
      "catalystHeadline": null,
      "breakout": false,
      "breakoutLevel": 161.47999572753906,
      "volumeSpike2x": false,
      "quoteTimestamp": "2026-07-03 00:00:00+02:00",
      "signal": "Hold",
      "dataSource": "Yahoo Finance / yfinance"
    },
    {
      "company": "Siemens AG",
      "ticker": "SIE.DE",
      "symbol": "SIE.DE",
      "column": "industrial",
      "currentPrice": 284.1000061035156,
      "change": 7.2,
      "percentChange": 2.6002,
      "high": 284.6499938964844,
      "low": 280.3999938964844,
      "open": 282.3999938964844,
      "prevClose": 276.8999938964844,
      "volume": 707250,
      "avgVolume20": 1127316,
      "avgDollarVolume20": 320270610,
      "liquid": true,
      "catalyst": true,
      "catalystHeadline": null,
      "breakout": false,
      "breakoutLevel": 281.1499938964844,
      "volumeSpike2x": false,
      "quoteTimestamp": "2026-07-03 00:00:00+02:00",
      "signal": "Hold",
      "dataSource": "Yahoo Finance / yfinance"
    },
    {
      "company": "Deutsche Telekom AG",
      "ticker": "DTE.DE",
      "symbol": "DTE.DE",
      "column": "telecom",
      "currentPrice": 25.139999389648438,
      "change": 0.04,
      "percentChange": 0.1594,
      "high": 25.329999923706055,
      "low": 24.8799991607666,
      "open": 25.049999237060547,
      "prevClose": 25.100000381469727,
      "volume": 6528127,
      "avgVolume20": 8499814,
      "avgDollarVolume20": 213685307,
      "liquid": true,
      "catalyst": true,
      "catalystHeadline": null,
      "breakout": false,
      "breakoutLevel": 28.6299991607666,
      "volumeSpike2x": false,
      "quoteTimestamp": "2026-07-03 00:00:00+02:00",
      "signal": "Hold",
      "dataSource": "Yahoo Finance / yfinance"
    },
    {
      "company": "Allianz SE",
      "ticker": "ALV.DE",
      "symbol": "ALV.DE",
      "column": "insurance",
      "currentPrice": 419.79998779296875,
      "change": 1.4,
      "percentChange": 0.3346,
      "high": 421.5,
      "low": 417.3999938964844,
      "open": 419.20001220703125,
      "prevClose": 418.3999938964844,
      "volume": 388720,
      "avgVolume20": 611940,
      "avgDollarVolume20": 256892363,
      "liquid": true,
      "catalyst": true,
      "catalystHeadline": null,
      "breakout": false,
      "breakoutLevel": 418.3999938964844,
      "volumeSpike2x": false,
      "quoteTimestamp": "2026-07-03 00:00:00+02:00",
      "signal": "Hold",
      "dataSource": "Yahoo Finance / yfinance"
    },
    {
      "company": "Deutsche Boerse AG",
      "ticker": "DB1.DE",
      "symbol": "DB1.DE",
      "column": "exchange",
      "currentPrice": 249.8000030517578,
      "change": 2.9,
      "percentChange": 1.1746,
      "high": 251.39999389648438,
      "low": 245.8000030517578,
      "open": 247.60000610351562,
      "prevClose": 246.89999389648438,
      "volume": 232740,
      "avgVolume20": 376290,
      "avgDollarVolume20": 93997281,
      "liquid": true,
      "catalyst": true,
      "catalystHeadline": null,
      "breakout": false,
      "breakoutLevel": 249.5,
      "volumeSpike2x": false,
      "quoteTimestamp": "2026-07-03 00:00:00+02:00",
      "signal": "Hold",
      "dataSource": "Yahoo Finance / yfinance"
    },
    {
      "company": "Mercedes-Benz Group AG",
      "ticker": "MBG.DE",
      "symbol": "MBG.DE",
      "column": "auto",
      "currentPrice": 45.2400016784668,
      "change": 0.415,
      "percentChange": 0.9258,
      "high": 45.560001373291016,
      "low": 45.029998779296875,
      "open": 45.14500045776367,
      "prevClose": 44.82500076293945,
      "volume": 1167470,
      "avgVolume20": 2730447,
      "avgDollarVolume20": 123525447,
      "liquid": true,
      "catalyst": true,
      "catalystHeadline": null,
      "breakout": false,
      "breakoutLevel": 49.375,
      "volumeSpike2x": false,
      "quoteTimestamp": "2026-07-03 00:00:00+02:00",
      "signal": "Hold",
      "dataSource": "Yahoo Finance / yfinance"
    },
    {
      "company": "Volkswagen AG Pref",
      "ticker": "VOW3.DE",
      "symbol": "VOW3.DE",
      "column": "auto",
      "currentPrice": 74.66000366210938,
      "change": 1.36,
      "percentChange": 1.8554,
      "high": 74.81999969482422,
      "low": 73.68000030517578,
      "open": 73.9000015258789,
      "prevClose": 73.30000305175781,
      "volume": 845592,
      "avgVolume20": 1363274,
      "avgDollarVolume20": 101782027,
      "liquid": true,
      "catalyst": true,
      "catalystHeadline": null,
      "breakout": false,
      "breakoutLevel": 90.41999816894531,
      "volumeSpike2x": false,
      "quoteTimestamp": "2026-07-03 00:00:00+02:00",
      "signal": "Hold",
      "dataSource": "Yahoo Finance / yfinance"
    },
    {
      "company": "BMW AG Pref",
      "ticker": "BMW.DE",
      "symbol": "BMW.DE",
      "column": "auto",
      "currentPrice": 60.560001373291016,
      "change": 0.36,
      "percentChange": 0.598,
      "high": 61.31999969482422,
      "low": 60.15999984741211,
      "open": 60.5,
      "prevClose": 60.20000076293945,
      "volume": 1319768,
      "avgVolume20": 2115652,
      "avgDollarVolume20": 128123909,
      "liquid": true,
      "catalyst": true,
      "catalystHeadline": null,
      "breakout": false,
      "breakoutLevel": 70.37999725341797,
      "volumeSpike2x": false,
      "quoteTimestamp": "2026-07-03 00:00:00+02:00",
      "signal": "Hold",
      "dataSource": "Yahoo Finance / yfinance"
    },
    {
      "company": "Infineon Technologies AG",
      "ticker": "IFX.DE",
      "symbol": "IFX.DE",
      "column": "semiconductor",
      "currentPrice": 77.37999725341797,
      "change": 1.03,
      "percentChange": 1.349,
      "high": 78.30999755859375,
      "low": 76.91000366210938,
      "open": 77.52999877929688,
      "prevClose": 76.3499984741211,
      "volume": 2824473,
      "avgVolume20": 5263004,
      "avgDollarVolume20": 407251227,
      "liquid": true,
      "catalyst": true,
      "catalystHeadline": null,
      "breakout": false,
      "breakoutLevel": 85.94000244140625,
      "volumeSpike2x": false,
      "quoteTimestamp": "2026-07-03 00:00:00+02:00",
      "signal": "Hold",
      "dataSource": "Yahoo Finance / yfinance"
    },
    {
      "company": "BASF SE",
      "ticker": "BAS.DE",
      "symbol": "BAS.DE",
      "column": "chemicals",
      "currentPrice": 47.779998779296875,
      "change": 0.14,
      "percentChange": 0.2939,
      "high": 48.08000183105469,
      "low": 47.43000030517578,
      "open": 47.94499969482422,
      "prevClose": 47.63999938964844,
      "volume": 1280677,
      "avgVolume20": 2405814,
      "avgDollarVolume20": 114949780,
      "liquid": true,
      "catalyst": true,
      "catalystHeadline": null,
      "breakout": false,
      "breakoutLevel": 50.97999954223633,
      "volumeSpike2x": false,
      "quoteTimestamp": "2026-07-03 00:00:00+02:00",
      "signal": "Hold",
      "dataSource": "Yahoo Finance / yfinance"
    },
    {
      "company": "Bayer AG",
      "ticker": "BAYN.DE",
      "symbol": "BAYN.DE",
      "column": "healthcare",
      "currentPrice": 53.36000061035156,
      "change": 0.0,
      "percentChange": 0.0,
      "high": 53.91999816894531,
      "low": 52.63999938964844,
      "open": 53.47999954223633,
      "prevClose": 53.36000061035156,
      "volume": 4165468,
      "avgVolume20": 4262263,
      "avgDollarVolume20": 227434335,
      "liquid": true,
      "catalyst": true,
      "catalystHeadline": null,
      "breakout": false,
      "breakoutLevel": 53.36000061035156,
      "volumeSpike2x": false,
      "quoteTimestamp": "2026-07-03 00:00:00+02:00",
      "signal": "Hold",
      "dataSource": "Yahoo Finance / yfinance"
    },
    {
      "company": "Rheinmetall AG",
      "ticker": "RHM.DE",
      "symbol": "RHM.DE",
      "column": "defense",
      "currentPrice": 1093.4000244140625,
      "change": -21.6,
      "percentChange": -1.9372,
      "high": 1121.0,
      "low": 1073.0,
      "open": 1117.199951171875,
      "prevClose": 1115.0,
      "volume": 243940,
      "avgVolume20": 298394,
      "avgDollarVolume20": 326263734,
      "liquid": true,
      "catalyst": true,
      "catalystHeadline": null,
      "breakout": false,
      "breakoutLevel": 1220.0,
      "volumeSpike2x": false,
      "quoteTimestamp": "2026-07-03 00:00:00+02:00",
      "signal": "Hold",
      "dataSource": "Yahoo Finance / yfinance"
    },
    {
      "company": "Airbus SE",
      "ticker": "AIR.PA",
      "symbol": "AIR.PA",
      "column": "aerospace",
      "currentPrice": 206.14999389648438,
      "change": 2.25,
      "percentChange": 1.1035,
      "high": 209.1999969482422,
      "low": 204.9499969482422,
      "open": 208.0,
      "prevClose": 203.89999389648438,
      "volume": 794284,
      "avgVolume20": 1258099,
      "avgDollarVolume20": 259357132,
      "liquid": true,
      "catalyst": true,
      "catalystHeadline": null,
      "breakout": false,
      "breakoutLevel": 203.89999389648438,
      "volumeSpike2x": false,
      "quoteTimestamp": "2026-07-03 00:00:00+02:00",
      "signal": "Hold",
      "dataSource": "Yahoo Finance / yfinance"
    },
    {
      "company": "ASML Holding N.V.",
      "ticker": "ASML.AS",
      "symbol": "ASML.AS",
      "column": "semiconductor",
      "currentPrice": 1634.4000244140625,
      "change": 56.6,
      "percentChange": 3.5873,
      "high": 1641.4000244140625,
      "low": 1588.4000244140625,
      "open": 1588.4000244140625,
      "prevClose": 1577.800048828125,
      "volume": 270434,
      "avgVolume20": 889555,
      "avgDollarVolume20": 1453888877,
      "liquid": true,
      "catalyst": true,
      "catalystHeadline": null,
      "breakout": false,
      "breakoutLevel": 1721.4000244140625,
      "volumeSpike2x": false,
      "quoteTimestamp": "2026-07-03 00:00:00+02:00",
      "signal": "Hold",
      "dataSource": "Yahoo Finance / yfinance"
    },
    {
      "company": "BE Semiconductor Industries N.V.",
      "ticker": "BESI.AS",
      "symbol": "BESI.AS",
      "column": "semiconductor",
      "currentPrice": 273.1000061035156,
      "change": 11.1,
      "percentChange": 4.2366,
      "high": 275.1000061035156,
      "low": 266.20001220703125,
      "open": 266.20001220703125,
      "prevClose": 262.0,
      "volume": 225799,
      "avgVolume20": 448990,
      "avgDollarVolume20": 122619213,
      "liquid": true,
      "catalyst": true,
      "catalystHeadline": null,
      "breakout": false,
      "breakoutLevel": 320.29998779296875,
      "volumeSpike2x": false,
      "quoteTimestamp": "2026-07-03 00:00:00+02:00",
      "signal": "Hold",
      "dataSource": "Yahoo Finance / yfinance"
    },
    {
      "company": "STMicroelectronics N.V.",
      "ticker": "STMPA.PA",
      "symbol": "STMPA.PA",
      "column": "semiconductor",
      "currentPrice": 62.779998779296875,
      "change": 1.0,
      "percentChange": 1.6186,
      "high": 62.900001525878906,
      "low": 60.810001373291016,
      "open": 61.06999969482422,
      "prevClose": 61.779998779296875,
      "volume": 1449492,
      "avgVolume20": 3329958,
      "avgDollarVolume20": 209054740,
      "liquid": true,
      "catalyst": true,
      "catalystHeadline": null,
      "breakout": false,
      "breakoutLevel": 69.38999938964844,
      "volumeSpike2x": false,
      "quoteTimestamp": "2026-07-03 00:00:00+02:00",
      "signal": "Hold",
      "dataSource": "Yahoo Finance / yfinance"
    },
    {
      "company": "Dassault Systemes SE",
      "ticker": "DSY.PA",
      "symbol": "DSY.PA",
      "column": "software",
      "currentPrice": 18.4950008392334,
      "change": -0.175,
      "percentChange": -0.9373,
      "high": 18.700000762939453,
      "low": 18.485000610351562,
      "open": 18.639999389648438,
      "prevClose": 18.670000076293945,
      "volume": 859288,
      "avgVolume20": 2311040,
      "avgDollarVolume20": 42742687,
      "liquid": true,
      "catalyst": true,
      "catalystHeadline": null,
      "breakout": false,
      "breakoutLevel": 19.895000457763672,
      "volumeSpike2x": false,
      "quoteTimestamp": "2026-07-03 00:00:00+02:00",
      "signal": "Hold",
      "dataSource": "Yahoo Finance / yfinance"
    },
    {
      "company": "Schneider Electric SE",
      "ticker": "SU.PA",
      "symbol": "SU.PA",
      "column": "industrial",
      "currentPrice": 280.1000061035156,
      "change": 4.2,
      "percentChange": 1.5223,
      "high": 281.70001220703125,
      "low": 274.6499938964844,
      "open": 275.3500061035156,
      "prevClose": 275.8999938964844,
      "volume": 621910,
      "avgVolume20": 1063131,
      "avgDollarVolume20": 297783042,
      "liquid": true,
      "catalyst": true,
      "catalystHeadline": null,
      "breakout": false,
      "breakoutLevel": 292.75,
      "volumeSpike2x": false,
      "quoteTimestamp": "2026-07-03 00:00:00+02:00",
      "signal": "Hold",
      "dataSource": "Yahoo Finance / yfinance"
    },
    {
      "company": "Safran SA",
      "ticker": "SAF.PA",
      "symbol": "SAF.PA",
      "column": "aerospace",
      "currentPrice": 356.70001220703125,
      "change": 3.4,
      "percentChange": 0.9624,
      "high": 358.20001220703125,
      "low": 353.1000061035156,
      "open": 356.1000061035156,
      "prevClose": 353.29998779296875,
      "volume": 528697,
      "avgVolume20": 778429,
      "avgDollarVolume20": 277665652,
      "liquid": true,
      "catalyst": true,
      "catalystHeadline": null,
      "breakout": false,
      "breakoutLevel": 353.29998779296875,
      "volumeSpike2x": false,
      "quoteTimestamp": "2026-07-03 00:00:00+02:00",
      "signal": "Hold",
      "dataSource": "Yahoo Finance / yfinance"
    },
    {
      "company": "Euronext N.V.",
      "ticker": "ENX.PA",
      "symbol": "ENX.PA",
      "column": "exchange",
      "currentPrice": 147.6999969482422,
      "change": 2.7,
      "percentChange": 1.8621,
      "high": 147.89999389648438,
      "low": 145.10000610351562,
      "open": 146.10000610351562,
      "prevClose": 145.0,
      "volume": 196479,
      "avgVolume20": 210491,
      "avgDollarVolume20": 31089542,
      "liquid": true,
      "catalyst": true,
      "catalystHeadline": null,
      "breakout": false,
      "breakoutLevel": 148.5,
      "volumeSpike2x": false,
      "quoteTimestamp": "2026-07-03 00:00:00+02:00",
      "signal": "Hold",
      "dataSource": "Yahoo Finance / yfinance"
    },
    {
      "company": "Rolls-Royce Holdings plc",
      "ticker": "RR.L",
      "symbol": "RR.L",
      "column": "aerospace",
      "currentPrice": 1504.199951171875,
      "change": 29.0,
      "percentChange": 1.9658,
      "high": 1504.199951171875,
      "low": 1478.5999755859375,
      "open": 1488.800048828125,
      "prevClose": 1475.199951171875,
      "volume": 10723720,
      "avgVolume20": 29384885,
      "avgDollarVolume20": 44200742733,
      "liquid": true,
      "catalyst": true,
      "catalystHeadline": null,
      "breakout": false,
      "breakoutLevel": 1475.199951171875,
      "volumeSpike2x": false,
      "quoteTimestamp": "2026-07-03 00:00:00+01:00",
      "signal": "Hold",
      "dataSource": "Yahoo Finance / yfinance"
    },
    {
      "company": "BAE Systems plc",
      "ticker": "BA.L",
      "symbol": "BA.L",
      "column": "defense",
      "currentPrice": 1981.5,
      "change": -1.0,
      "percentChange": -0.0504,
      "high": 2002.0,
      "low": 1959.0,
      "open": 1998.5,
      "prevClose": 1982.5,
      "volume": 3206450,
      "avgVolume20": 7651462,
      "avgDollarVolume20": 15161372448,
      "liquid": true,
      "catalyst": true,
      "catalystHeadline": null,
      "breakout": false,
      "breakoutLevel": 1982.5,
      "volumeSpike2x": false,
      "quoteTimestamp": "2026-07-03 00:00:00+01:00",
      "signal": "Hold",
      "dataSource": "Yahoo Finance / yfinance"
    },
    {
      "company": "RELX PLC",
      "ticker": "REL.L",
      "symbol": "REL.L",
      "column": "information",
      "currentPrice": 2334.0,
      "change": -19.0,
      "percentChange": -0.8075,
      "high": 2380.0,
      "low": 2321.0,
      "open": 2371.0,
      "prevClose": 2353.0,
      "volume": 2554563,
      "avgVolume20": 5280606,
      "avgDollarVolume20": 12324934988,
      "liquid": true,
      "catalyst": true,
      "catalystHeadline": null,
      "breakout": false,
      "breakoutLevel": 2616.0,
      "volumeSpike2x": false,
      "quoteTimestamp": "2026-07-03 00:00:00+01:00",
      "signal": "Hold",
      "dataSource": "Yahoo Finance / yfinance"
    },
    {
      "company": "ABB Ltd",
      "ticker": "ABBN.SW",
      "symbol": "ABBN.SW",
      "column": "industrial",
      "currentPrice": 87.37999725341797,
      "change": 2.46,
      "percentChange": 2.8968,
      "high": 87.4000015258789,
      "low": 85.30000305175781,
      "open": 85.69999694824219,
      "prevClose": 84.91999816894531,
      "volume": 2098591,
      "avgVolume20": 2628025,
      "avgDollarVolume20": 229636813,
      "liquid": true,
      "catalyst": true,
      "catalystHeadline": null,
      "breakout": false,
      "breakoutLevel": 88.55999755859375,
      "volumeSpike2x": false,
      "quoteTimestamp": "2026-07-03 00:00:00+02:00",
      "signal": "Hold",
      "dataSource": "Yahoo Finance / yfinance"
    }
  ],
  "errors": []
}