{
  "updatedAt": 1780758490,
  "source": "yahoo_finance",
  "settings": {
    "liquidityThreshold": 10000000,
    "breakoutWindow": 20,
    "breakoutPct": 0.02,
    "volumeSpikeMultiplier": 2.0
  },
  "items": [
    {
      "company": "SAP SE",
      "ticker": "SAP.DE",
      "symbol": "SAP.DE",
      "column": "software",
      "currentPrice": 161.47999572753906,
      "change": -3.02,
      "percentChange": -1.8359,
      "high": 168.74000549316406,
      "low": 161.47999572753906,
      "open": 163.74000549316406,
      "prevClose": 164.5,
      "volume": 2968649,
      "avgVolume20": 3005570,
      "avgDollarVolume20": 485339390,
      "liquid": true,
      "catalyst": true,
      "catalystHeadline": null,
      "breakout": false,
      "breakoutLevel": 167.89999389648438,
      "volumeSpike2x": false,
      "quoteTimestamp": "2026-06-05 00:00:00+02:00",
      "signal": "Hold",
      "dataSource": "Yahoo Finance / yfinance"
    },
    {
      "company": "Siemens AG",
      "ticker": "SIE.DE",
      "symbol": "SIE.DE",
      "column": "industrial",
      "currentPrice": 268.79998779296875,
      "change": -3.25,
      "percentChange": -1.1946,
      "high": 272.3999938964844,
      "low": 267.95001220703125,
      "open": 272.3500061035156,
      "prevClose": 272.04998779296875,
      "volume": 654828,
      "avgVolume20": 1019815,
      "avgDollarVolume20": 274126313,
      "liquid": true,
      "catalyst": true,
      "catalystHeadline": null,
      "breakout": false,
      "breakoutLevel": 278.70001220703125,
      "volumeSpike2x": false,
      "quoteTimestamp": "2026-06-05 00:00:00+02:00",
      "signal": "Hold",
      "dataSource": "Yahoo Finance / yfinance"
    },
    {
      "company": "Deutsche Telekom AG",
      "ticker": "DTE.DE",
      "symbol": "DTE.DE",
      "column": "telecom",
      "currentPrice": 27.65999984741211,
      "change": -0.17,
      "percentChange": -0.6109,
      "high": 28.209999084472656,
      "low": 27.600000381469727,
      "open": 27.8799991607666,
      "prevClose": 27.829999923706055,
      "volume": 6734516,
      "avgVolume20": 6835231,
      "avgDollarVolume20": 189062488,
      "liquid": true,
      "catalyst": true,
      "catalystHeadline": null,
      "breakout": false,
      "breakoutLevel": 29.450000762939453,
      "volumeSpike2x": false,
      "quoteTimestamp": "2026-06-05 00:00:00+02:00",
      "signal": "Hold",
      "dataSource": "Yahoo Finance / yfinance"
    },
    {
      "company": "Allianz SE",
      "ticker": "ALV.DE",
      "symbol": "ALV.DE",
      "column": "insurance",
      "currentPrice": 372.79998779296875,
      "change": 1.5,
      "percentChange": 0.404,
      "high": 373.3999938964844,
      "low": 370.79998779296875,
      "open": 371.70001220703125,
      "prevClose": 371.29998779296875,
      "volume": 381342,
      "avgVolume20": 695125,
      "avgDollarVolume20": 259142554,
      "liquid": true,
      "catalyst": true,
      "catalystHeadline": null,
      "breakout": false,
      "breakoutLevel": 391.0,
      "volumeSpike2x": false,
      "quoteTimestamp": "2026-06-05 00:00:00+02:00",
      "signal": "Hold",
      "dataSource": "Yahoo Finance / yfinance"
    },
    {
      "company": "Deutsche Boerse AG",
      "ticker": "DB1.DE",
      "symbol": "DB1.DE",
      "column": "exchange",
      "currentPrice": 245.89999389648438,
      "change": 0.6,
      "percentChange": 0.2446,
      "high": 250.5,
      "low": 245.39999389648438,
      "open": 245.6999969482422,
      "prevClose": 245.3000030517578,
      "volume": 292370,
      "avgVolume20": 404468,
      "avgDollarVolume20": 99458593,
      "liquid": true,
      "catalyst": true,
      "catalystHeadline": null,
      "breakout": false,
      "breakoutLevel": 258.0,
      "volumeSpike2x": false,
      "quoteTimestamp": "2026-06-05 00:00:00+02:00",
      "signal": "Hold",
      "dataSource": "Yahoo Finance / yfinance"
    },
    {
      "company": "Mercedes-Benz Group AG",
      "ticker": "MBG.DE",
      "symbol": "MBG.DE",
      "column": "auto",
      "currentPrice": 47.994998931884766,
      "change": -1.08,
      "percentChange": -2.2007,
      "high": 49.33000183105469,
      "low": 47.86000061035156,
      "open": 49.18000030517578,
      "prevClose": 49.07500076293945,
      "volume": 2316429,
      "avgVolume20": 2503080,
      "avgDollarVolume20": 120135312,
      "liquid": true,
      "catalyst": true,
      "catalystHeadline": null,
      "breakout": false,
      "breakoutLevel": 52.709999084472656,
      "volumeSpike2x": false,
      "quoteTimestamp": "2026-06-05 00:00:00+02:00",
      "signal": "Hold",
      "dataSource": "Yahoo Finance / yfinance"
    },
    {
      "company": "Volkswagen AG Pref",
      "ticker": "VOW3.DE",
      "symbol": "VOW3.DE",
      "column": "auto",
      "currentPrice": 87.83999633789062,
      "change": -0.76,
      "percentChange": -0.8578,
      "high": 89.0999984741211,
      "low": 87.54000091552734,
      "open": 89.0,
      "prevClose": 88.5999984741211,
      "volume": 827145,
      "avgVolume20": 771460,
      "avgDollarVolume20": 67765070,
      "liquid": true,
      "catalyst": true,
      "catalystHeadline": null,
      "breakout": false,
      "breakoutLevel": 92.55999755859375,
      "volumeSpike2x": false,
      "quoteTimestamp": "2026-06-05 00:00:00+02:00",
      "signal": "Hold",
      "dataSource": "Yahoo Finance / yfinance"
    },
    {
      "company": "BMW AG Pref",
      "ticker": "BMW.DE",
      "symbol": "BMW.DE",
      "column": "auto",
      "currentPrice": 70.37999725341797,
      "change": 0.14,
      "percentChange": 0.1993,
      "high": 71.05999755859375,
      "low": 70.08000183105469,
      "open": 70.18000030517578,
      "prevClose": 70.23999786376953,
      "volume": 1211685,
      "avgVolume20": 1243235,
      "avgDollarVolume20": 87498869,
      "liquid": true,
      "catalyst": true,
      "catalystHeadline": null,
      "breakout": false,
      "breakoutLevel": 81.81999969482422,
      "volumeSpike2x": false,
      "quoteTimestamp": "2026-06-05 00:00:00+02:00",
      "signal": "Hold",
      "dataSource": "Yahoo Finance / yfinance"
    },
    {
      "company": "Infineon Technologies AG",
      "ticker": "IFX.DE",
      "symbol": "IFX.DE",
      "column": "semiconductor",
      "currentPrice": 77.30000305175781,
      "change": -7.75,
      "percentChange": -9.1123,
      "high": 81.91999816894531,
      "low": 76.93000030517578,
      "open": 80.5,
      "prevClose": 85.05000305175781,
      "volume": 8277564,
      "avgVolume20": 6533298,
      "avgDollarVolume20": 505023990,
      "liquid": true,
      "catalyst": true,
      "catalystHeadline": null,
      "breakout": false,
      "breakoutLevel": 88.0,
      "volumeSpike2x": false,
      "quoteTimestamp": "2026-06-05 00:00:00+02:00",
      "signal": "Hold",
      "dataSource": "Yahoo Finance / yfinance"
    },
    {
      "company": "BASF SE",
      "ticker": "BAS.DE",
      "symbol": "BAS.DE",
      "column": "chemicals",
      "currentPrice": 50.97999954223633,
      "change": 0.33,
      "percentChange": 0.6515,
      "high": 51.47999954223633,
      "low": 50.779998779296875,
      "open": 50.880001068115234,
      "prevClose": 50.650001525878906,
      "volume": 1992221,
      "avgVolume20": 2453902,
      "avgDollarVolume20": 125099908,
      "liquid": true,
      "catalyst": true,
      "catalystHeadline": null,
      "breakout": false,
      "breakoutLevel": 54.0,
      "volumeSpike2x": false,
      "quoteTimestamp": "2026-06-05 00:00:00+02:00",
      "signal": "Hold",
      "dataSource": "Yahoo Finance / yfinance"
    },
    {
      "company": "Bayer AG",
      "ticker": "BAYN.DE",
      "symbol": "BAYN.DE",
      "column": "healthcare",
      "currentPrice": 36.15999984741211,
      "change": 0.6,
      "percentChange": 1.6873,
      "high": 36.36000061035156,
      "low": 35.29999923706055,
      "open": 35.439998626708984,
      "prevClose": 35.560001373291016,
      "volume": 2211444,
      "avgVolume20": 2808642,
      "avgDollarVolume20": 101560487,
      "liquid": true,
      "catalyst": true,
      "catalystHeadline": null,
      "breakout": false,
      "breakoutLevel": 39.22999954223633,
      "volumeSpike2x": false,
      "quoteTimestamp": "2026-06-05 00:00:00+02:00",
      "signal": "Hold",
      "dataSource": "Yahoo Finance / yfinance"
    },
    {
      "company": "Rheinmetall AG",
      "ticker": "RHM.DE",
      "symbol": "RHM.DE",
      "column": "defense",
      "currentPrice": 1209.800048828125,
      "change": 19.6001,
      "percentChange": 1.6468,
      "high": 1221.199951171875,
      "low": 1180.800048828125,
      "open": 1187.0,
      "prevClose": 1190.199951171875,
      "volume": 146109,
      "avgVolume20": 278109,
      "avgDollarVolume20": 336456221,
      "liquid": true,
      "catalyst": true,
      "catalystHeadline": null,
      "breakout": false,
      "breakoutLevel": 1293.4000244140625,
      "volumeSpike2x": false,
      "quoteTimestamp": "2026-06-05 00:00:00+02:00",
      "signal": "Hold",
      "dataSource": "Yahoo Finance / yfinance"
    },
    {
      "company": "Airbus SE",
      "ticker": "AIR.PA",
      "symbol": "AIR.PA",
      "column": "aerospace",
      "currentPrice": 178.9600067138672,
      "change": 1.96,
      "percentChange": 1.1073,
      "high": 179.63999938964844,
      "low": 176.83999633789062,
      "open": 177.97999572753906,
      "prevClose": 177.0,
      "volume": 1239190,
      "avgVolume20": 1318390,
      "avgDollarVolume20": 235939119,
      "liquid": true,
      "catalyst": true,
      "catalystHeadline": null,
      "breakout": false,
      "breakoutLevel": 179.8800048828125,
      "volumeSpike2x": false,
      "quoteTimestamp": "2026-06-05 00:00:00+02:00",
      "signal": "Hold",
      "dataSource": "Yahoo Finance / yfinance"
    },
    {
      "company": "ASML Holding N.V.",
      "ticker": "ASML.AS",
      "symbol": "ASML.AS",
      "column": "semiconductor",
      "currentPrice": 1462.199951171875,
      "change": -35.8,
      "percentChange": -2.3899,
      "high": 1475.0,
      "low": 1444.800048828125,
      "open": 1468.0,
      "prevClose": 1498.0,
      "volume": 665378,
      "avgVolume20": 624971,
      "avgDollarVolume20": 913832858,
      "liquid": true,
      "catalyst": true,
      "catalystHeadline": null,
      "breakout": false,
      "breakoutLevel": 1498.0,
      "volumeSpike2x": false,
      "quoteTimestamp": "2026-06-05 00:00:00+02:00",
      "signal": "Hold",
      "dataSource": "Yahoo Finance / yfinance"
    },
    {
      "company": "BE Semiconductor Industries N.V.",
      "ticker": "BESI.AS",
      "symbol": "BESI.AS",
      "column": "semiconductor",
      "currentPrice": 271.3999938964844,
      "change": -12.2,
      "percentChange": -4.3018,
      "high": 281.0,
      "low": 271.0,
      "open": 281.0,
      "prevClose": 283.6000061035156,
      "volume": 302582,
      "avgVolume20": 385707,
      "avgDollarVolume20": 104680850,
      "liquid": true,
      "catalyst": true,
      "catalystHeadline": null,
      "breakout": false,
      "breakoutLevel": 288.3999938964844,
      "volumeSpike2x": false,
      "quoteTimestamp": "2026-06-05 00:00:00+02:00",
      "signal": "Hold",
      "dataSource": "Yahoo Finance / yfinance"
    },
    {
      "company": "STMicroelectronics N.V.",
      "ticker": "STMPA.PA",
      "symbol": "STMPA.PA",
      "column": "semiconductor",
      "currentPrice": 62.81999969482422,
      "change": -3.9,
      "percentChange": -5.8453,
      "high": 65.33999633789062,
      "low": 62.720001220703125,
      "open": 65.29000091552734,
      "prevClose": 66.72000122070312,
      "volume": 3552916,
      "avgVolume20": 3787779,
      "avgDollarVolume20": 237948272,
      "liquid": true,
      "catalyst": true,
      "catalystHeadline": null,
      "breakout": false,
      "breakoutLevel": 68.48999786376953,
      "volumeSpike2x": false,
      "quoteTimestamp": "2026-06-05 00:00:00+02:00",
      "signal": "Hold",
      "dataSource": "Yahoo Finance / yfinance"
    },
    {
      "company": "Dassault Systemes SE",
      "ticker": "DSY.PA",
      "symbol": "DSY.PA",
      "column": "software",
      "currentPrice": 19.71500015258789,
      "change": -0.445,
      "percentChange": -2.2073,
      "high": 20.56999969482422,
      "low": 19.71500015258789,
      "open": 19.989999771118164,
      "prevClose": 20.15999984741211,
      "volume": 1833107,
      "avgVolume20": 2732180,
      "avgDollarVolume20": 53864935,
      "liquid": true,
      "catalyst": true,
      "catalystHeadline": null,
      "breakout": false,
      "breakoutLevel": 20.649999618530273,
      "volumeSpike2x": false,
      "quoteTimestamp": "2026-06-05 00:00:00+02:00",
      "signal": "Hold",
      "dataSource": "Yahoo Finance / yfinance"
    },
    {
      "company": "Schneider Electric SE",
      "ticker": "SU.PA",
      "symbol": "SU.PA",
      "column": "industrial",
      "currentPrice": 269.04998779296875,
      "change": -12.8,
      "percentChange": -4.5414,
      "high": 281.29998779296875,
      "low": 268.54998779296875,
      "open": 281.20001220703125,
      "prevClose": 281.8500061035156,
      "volume": 1084866,
      "avgVolume20": 916992,
      "avgDollarVolume20": 246716686,
      "liquid": true,
      "catalyst": true,
      "catalystHeadline": null,
      "breakout": false,
      "breakoutLevel": 287.1499938964844,
      "volumeSpike2x": false,
      "quoteTimestamp": "2026-06-05 00:00:00+02:00",
      "signal": "Hold",
      "dataSource": "Yahoo Finance / yfinance"
    },
    {
      "company": "Safran SA",
      "ticker": "SAF.PA",
      "symbol": "SAF.PA",
      "column": "aerospace",
      "currentPrice": 298.5,
      "change": -1.8,
      "percentChange": -0.5994,
      "high": 302.0,
      "low": 297.5,
      "open": 301.20001220703125,
      "prevClose": 300.29998779296875,
      "volume": 474814,
      "avgVolume20": 632840,
      "avgDollarVolume20": 188902695,
      "liquid": true,
      "catalyst": true,
      "catalystHeadline": null,
      "breakout": false,
      "breakoutLevel": 305.70001220703125,
      "volumeSpike2x": false,
      "quoteTimestamp": "2026-06-05 00:00:00+02:00",
      "signal": "Hold",
      "dataSource": "Yahoo Finance / yfinance"
    },
    {
      "company": "Euronext N.V.",
      "ticker": "ENX.PA",
      "symbol": "ENX.PA",
      "column": "exchange",
      "currentPrice": 142.1999969482422,
      "change": 2.1,
      "percentChange": 1.4989,
      "high": 143.60000610351562,
      "low": 140.39999389648438,
      "open": 140.39999389648438,
      "prevClose": 140.10000610351562,
      "volume": 228352,
      "avgVolume20": 243232,
      "avgDollarVolume20": 34587533,
      "liquid": true,
      "catalyst": true,
      "catalystHeadline": null,
      "breakout": false,
      "breakoutLevel": 150.1999969482422,
      "volumeSpike2x": false,
      "quoteTimestamp": "2026-06-05 00:00:00+02:00",
      "signal": "Hold",
      "dataSource": "Yahoo Finance / yfinance"
    },
    {
      "company": "Rolls-Royce Holdings plc",
      "ticker": "RR.L",
      "symbol": "RR.L",
      "column": "aerospace",
      "currentPrice": 1260.0,
      "change": -3.2,
      "percentChange": -0.2533,
      "high": 1277.199951171875,
      "low": 1253.199951171875,
      "open": 1267.800048828125,
      "prevClose": 1263.199951171875,
      "volume": 29097229,
      "avgVolume20": 29006100,
      "avgDollarVolume20": 36547685433,
      "liquid": true,
      "catalyst": true,
      "catalystHeadline": null,
      "breakout": false,
      "breakoutLevel": 1337.4000244140625,
      "volumeSpike2x": false,
      "quoteTimestamp": "2026-06-05 00:00:00+01:00",
      "signal": "Hold",
      "dataSource": "Yahoo Finance / yfinance"
    },
    {
      "company": "BAE Systems plc",
      "ticker": "BA.L",
      "symbol": "BA.L",
      "column": "defense",
      "currentPrice": 1930.5,
      "change": 14.5,
      "percentChange": 0.7568,
      "high": 1953.5,
      "low": 1921.427978515625,
      "open": 1924.0,
      "prevClose": 1916.0,
      "volume": 3354260,
      "avgVolume20": 5617796,
      "avgDollarVolume20": 10845154213,
      "liquid": true,
      "catalyst": true,
      "catalystHeadline": null,
      "breakout": false,
      "breakoutLevel": 2023.0,
      "volumeSpike2x": false,
      "quoteTimestamp": "2026-06-05 00:00:00+01:00",
      "signal": "Hold",
      "dataSource": "Yahoo Finance / yfinance"
    },
    {
      "company": "RELX PLC",
      "ticker": "REL.L",
      "symbol": "REL.L",
      "column": "information",
      "currentPrice": 2616.0,
      "change": 33.0,
      "percentChange": 1.2776,
      "high": 2654.0,
      "low": 2552.929931640625,
      "open": 2555.0,
      "prevClose": 2583.0,
      "volume": 4830257,
      "avgVolume20": 6355487,
      "avgDollarVolume20": 16625953730,
      "liquid": true,
      "catalyst": true,
      "catalystHeadline": null,
      "breakout": false,
      "breakoutLevel": 2583.0,
      "volumeSpike2x": false,
      "quoteTimestamp": "2026-06-05 00:00:00+01:00",
      "signal": "Hold",
      "dataSource": "Yahoo Finance / yfinance"
    },
    {
      "company": "ABB Ltd",
      "ticker": "ABBN.SW",
      "symbol": "ABBN.SW",
      "column": "industrial",
      "currentPrice": 83.0999984741211,
      "change": -1.56,
      "percentChange": -1.8427,
      "high": 84.36000061035156,
      "low": 82.58000183105469,
      "open": 84.36000061035156,
      "prevClose": 84.66000366210938,
      "volume": 1740267,
      "avgVolume20": 2284599,
      "avgDollarVolume20": 189850186,
      "liquid": true,
      "catalyst": true,
      "catalystHeadline": null,
      "breakout": false,
      "breakoutLevel": 86.0999984741211,
      "volumeSpike2x": false,
      "quoteTimestamp": "2026-06-05 00:00:00+02:00",
      "signal": "Hold",
      "dataSource": "Yahoo Finance / yfinance"
    }
  ],
  "errors": []
}