{
  "updatedAt": 1784284795,
  "source": "yahoo_finance",
  "settings": {
    "liquidityThreshold": 10000000,
    "breakoutWindow": 20,
    "breakoutPct": 0.02,
    "volumeSpikeMultiplier": 2.0
  },
  "items": [
    {
      "company": "SAP SE",
      "ticker": "SAP.DE",
      "symbol": "SAP.DE",
      "column": "software",
      "currentPrice": 138.0800018310547,
      "change": 0.44,
      "percentChange": 0.3197,
      "high": 141.5399932861328,
      "low": 137.94000244140625,
      "open": 140.60000610351562,
      "prevClose": 137.63999938964844,
      "volume": 822489,
      "avgVolume20": 2627225,
      "avgDollarVolume20": 362767247,
      "liquid": true,
      "catalyst": true,
      "catalystHeadline": null,
      "breakout": false,
      "breakoutLevel": 143.89999389648438,
      "volumeSpike2x": false,
      "quoteTimestamp": "2026-07-17 00:00:00+02:00",
      "signal": "Hold",
      "dataSource": "Yahoo Finance / yfinance"
    },
    {
      "company": "Siemens AG",
      "ticker": "SIE.DE",
      "symbol": "SIE.DE",
      "column": "industrial",
      "currentPrice": 262.5,
      "change": -8.2,
      "percentChange": -3.0292,
      "high": 265.3500061035156,
      "low": 260.6499938964844,
      "open": 263.45001220703125,
      "prevClose": 270.70001220703125,
      "volume": 354811,
      "avgVolume20": 1011694,
      "avgDollarVolume20": 265569636,
      "liquid": true,
      "catalyst": true,
      "catalystHeadline": null,
      "breakout": false,
      "breakoutLevel": 284.1000061035156,
      "volumeSpike2x": false,
      "quoteTimestamp": "2026-07-17 00:00:00+02:00",
      "signal": "Hold",
      "dataSource": "Yahoo Finance / yfinance"
    },
    {
      "company": "Deutsche Telekom AG",
      "ticker": "DTE.DE",
      "symbol": "DTE.DE",
      "column": "telecom",
      "currentPrice": 27.260000228881836,
      "change": 0.58,
      "percentChange": 2.1739,
      "high": 27.40999984741211,
      "low": 26.799999237060547,
      "open": 26.81999969482422,
      "prevClose": 26.68000030517578,
      "volume": 2270208,
      "avgVolume20": 7613534,
      "avgDollarVolume20": 207544933,
      "liquid": true,
      "catalyst": true,
      "catalystHeadline": null,
      "breakout": false,
      "breakoutLevel": 26.739999771118164,
      "volumeSpike2x": false,
      "quoteTimestamp": "2026-07-17 00:00:00+02:00",
      "signal": "Hold",
      "dataSource": "Yahoo Finance / yfinance"
    },
    {
      "company": "Allianz SE",
      "ticker": "ALV.DE",
      "symbol": "ALV.DE",
      "column": "insurance",
      "currentPrice": 421.5,
      "change": 1.9,
      "percentChange": 0.4528,
      "high": 422.29998779296875,
      "low": 418.6000061035156,
      "open": 419.20001220703125,
      "prevClose": 419.6000061035156,
      "volume": 143852,
      "avgVolume20": 553262,
      "avgDollarVolume20": 233199954,
      "liquid": true,
      "catalyst": true,
      "catalystHeadline": null,
      "breakout": false,
      "breakoutLevel": 422.79998779296875,
      "volumeSpike2x": false,
      "quoteTimestamp": "2026-07-17 00:00:00+02:00",
      "signal": "Hold",
      "dataSource": "Yahoo Finance / yfinance"
    },
    {
      "company": "Deutsche Boerse AG",
      "ticker": "DB1.DE",
      "symbol": "DB1.DE",
      "column": "exchange",
      "currentPrice": 259.79998779296875,
      "change": -1.1,
      "percentChange": -0.4216,
      "high": 264.0,
      "low": 259.29998779296875,
      "open": 263.70001220703125,
      "prevClose": 260.8999938964844,
      "volume": 77982,
      "avgVolume20": 322961,
      "avgDollarVolume20": 83905173,
      "liquid": true,
      "catalyst": true,
      "catalystHeadline": null,
      "breakout": false,
      "breakoutLevel": 260.8999938964844,
      "volumeSpike2x": false,
      "quoteTimestamp": "2026-07-17 00:00:00+02:00",
      "signal": "Hold",
      "dataSource": "Yahoo Finance / yfinance"
    },
    {
      "company": "Mercedes-Benz Group AG",
      "ticker": "MBG.DE",
      "symbol": "MBG.DE",
      "column": "auto",
      "currentPrice": 45.880001068115234,
      "change": 0.02,
      "percentChange": 0.0436,
      "high": 46.25,
      "low": 45.57500076293945,
      "open": 45.79999923706055,
      "prevClose": 45.86000061035156,
      "volume": 692280,
      "avgVolume20": 2433681,
      "avgDollarVolume20": 111657273,
      "liquid": true,
      "catalyst": true,
      "catalystHeadline": null,
      "breakout": false,
      "breakoutLevel": 46.28499984741211,
      "volumeSpike2x": false,
      "quoteTimestamp": "2026-07-17 00:00:00+02:00",
      "signal": "Hold",
      "dataSource": "Yahoo Finance / yfinance"
    },
    {
      "company": "Volkswagen AG Pref",
      "ticker": "VOW3.DE",
      "symbol": "VOW3.DE",
      "column": "auto",
      "currentPrice": 73.26000213623047,
      "change": -0.2,
      "percentChange": -0.2723,
      "high": 73.81999969482422,
      "low": 73.0199966430664,
      "open": 73.27999877929688,
      "prevClose": 73.45999908447266,
      "volume": 146043,
      "avgVolume20": 1237527,
      "avgDollarVolume20": 90661238,
      "liquid": true,
      "catalyst": true,
      "catalystHeadline": null,
      "breakout": false,
      "breakoutLevel": 80.44000244140625,
      "volumeSpike2x": false,
      "quoteTimestamp": "2026-07-17 00:00:00+02:00",
      "signal": "Hold",
      "dataSource": "Yahoo Finance / yfinance"
    },
    {
      "company": "BMW AG Pref",
      "ticker": "BMW.DE",
      "symbol": "BMW.DE",
      "column": "auto",
      "currentPrice": 58.779998779296875,
      "change": 0.46,
      "percentChange": 0.7888,
      "high": 59.29999923706055,
      "low": 58.540000915527344,
      "open": 59.279998779296875,
      "prevClose": 58.31999969482422,
      "volume": 684527,
      "avgVolume20": 1754982,
      "avgDollarVolume20": 103157819,
      "liquid": true,
      "catalyst": true,
      "catalystHeadline": null,
      "breakout": false,
      "breakoutLevel": 61.060001373291016,
      "volumeSpike2x": false,
      "quoteTimestamp": "2026-07-17 00:00:00+02:00",
      "signal": "Hold",
      "dataSource": "Yahoo Finance / yfinance"
    },
    {
      "company": "Infineon Technologies AG",
      "ticker": "IFX.DE",
      "symbol": "IFX.DE",
      "column": "semiconductor",
      "currentPrice": 61.849998474121094,
      "change": -2.86,
      "percentChange": -4.4197,
      "high": 62.5,
      "low": 60.630001068115234,
      "open": 61.130001068115234,
      "prevClose": 64.70999908447266,
      "volume": 2167278,
      "avgVolume20": 4567105,
      "avgDollarVolume20": 282475459,
      "liquid": true,
      "catalyst": true,
      "catalystHeadline": null,
      "breakout": false,
      "breakoutLevel": 85.94000244140625,
      "volumeSpike2x": false,
      "quoteTimestamp": "2026-07-17 00:00:00+02:00",
      "signal": "Hold",
      "dataSource": "Yahoo Finance / yfinance"
    },
    {
      "company": "BASF SE",
      "ticker": "BAS.DE",
      "symbol": "BAS.DE",
      "column": "chemicals",
      "currentPrice": 48.45500183105469,
      "change": 0.04,
      "percentChange": 0.0826,
      "high": 48.720001220703125,
      "low": 48.20500183105469,
      "open": 48.625,
      "prevClose": 48.415000915527344,
      "volume": 914105,
      "avgVolume20": 2171258,
      "avgDollarVolume20": 105208291,
      "liquid": true,
      "catalyst": true,
      "catalystHeadline": null,
      "breakout": false,
      "breakoutLevel": 49.41999816894531,
      "volumeSpike2x": false,
      "quoteTimestamp": "2026-07-17 00:00:00+02:00",
      "signal": "Hold",
      "dataSource": "Yahoo Finance / yfinance"
    },
    {
      "company": "Bayer AG",
      "ticker": "BAYN.DE",
      "symbol": "BAYN.DE",
      "column": "healthcare",
      "currentPrice": 47.7599983215332,
      "change": 0.04,
      "percentChange": 0.0838,
      "high": 47.959999084472656,
      "low": 46.81999969482422,
      "open": 47.56999969482422,
      "prevClose": 47.720001220703125,
      "volume": 809073,
      "avgVolume20": 4234216,
      "avgDollarVolume20": 202226130,
      "liquid": true,
      "catalyst": true,
      "catalystHeadline": null,
      "breakout": false,
      "breakoutLevel": 53.36000061035156,
      "volumeSpike2x": false,
      "quoteTimestamp": "2026-07-17 00:00:00+02:00",
      "signal": "Hold",
      "dataSource": "Yahoo Finance / yfinance"
    },
    {
      "company": "Rheinmetall AG",
      "ticker": "RHM.DE",
      "symbol": "RHM.DE",
      "column": "defense",
      "currentPrice": 978.7999877929688,
      "change": 14.9,
      "percentChange": 1.5458,
      "high": 988.2000122070312,
      "low": 937.5999755859375,
      "open": 948.7000122070312,
      "prevClose": 963.9000244140625,
      "volume": 82578,
      "avgVolume20": 317241,
      "avgDollarVolume20": 310515536,
      "liquid": true,
      "catalyst": true,
      "catalystHeadline": null,
      "breakout": false,
      "breakoutLevel": 1202.5999755859375,
      "volumeSpike2x": false,
      "quoteTimestamp": "2026-07-17 00:00:00+02:00",
      "signal": "Hold",
      "dataSource": "Yahoo Finance / yfinance"
    },
    {
      "company": "Airbus SE",
      "ticker": "AIR.PA",
      "symbol": "AIR.PA",
      "column": "aerospace",
      "currentPrice": 192.74000549316406,
      "change": -2.88,
      "percentChange": -1.4722,
      "high": 194.6199951171875,
      "low": 191.83999633789062,
      "open": 193.1999969482422,
      "prevClose": 195.6199951171875,
      "volume": 287666,
      "avgVolume20": 1090658,
      "avgDollarVolume20": 210213419,
      "liquid": true,
      "catalyst": true,
      "catalystHeadline": null,
      "breakout": false,
      "breakoutLevel": 209.39999389648438,
      "volumeSpike2x": false,
      "quoteTimestamp": "2026-07-17 00:00:00+02:00",
      "signal": "Hold",
      "dataSource": "Yahoo Finance / yfinance"
    },
    {
      "company": "ASML Holding N.V.",
      "ticker": "ASML.AS",
      "symbol": "ASML.AS",
      "column": "semiconductor",
      "currentPrice": 1549.5999755859375,
      "change": -48.8,
      "percentChange": -3.0531,
      "high": 1553.4000244140625,
      "low": 1514.5999755859375,
      "open": 1536.0,
      "prevClose": 1598.4000244140625,
      "volume": 265161,
      "avgVolume20": 761907,
      "avgDollarVolume20": 1180651611,
      "liquid": true,
      "catalyst": true,
      "catalystHeadline": null,
      "breakout": false,
      "breakoutLevel": 1721.4000244140625,
      "volumeSpike2x": false,
      "quoteTimestamp": "2026-07-17 00:00:00+02:00",
      "signal": "Hold",
      "dataSource": "Yahoo Finance / yfinance"
    },
    {
      "company": "BE Semiconductor Industries N.V.",
      "ticker": "BESI.AS",
      "symbol": "BESI.AS",
      "column": "semiconductor",
      "currentPrice": 224.60000610351562,
      "change": -11.6,
      "percentChange": -4.9111,
      "high": 228.60000610351562,
      "low": 220.39999389648438,
      "open": 227.0,
      "prevClose": 236.1999969482422,
      "volume": 180523,
      "avgVolume20": 416006,
      "avgDollarVolume20": 93434973,
      "liquid": true,
      "catalyst": true,
      "catalystHeadline": null,
      "breakout": false,
      "breakoutLevel": 320.29998779296875,
      "volumeSpike2x": false,
      "quoteTimestamp": "2026-07-17 00:00:00+02:00",
      "signal": "Hold",
      "dataSource": "Yahoo Finance / yfinance"
    },
    {
      "company": "STMicroelectronics N.V.",
      "ticker": "STMPA.PA",
      "symbol": "STMPA.PA",
      "column": "semiconductor",
      "currentPrice": 52.61000061035156,
      "change": -3.38,
      "percentChange": -6.0368,
      "high": 53.58000183105469,
      "low": 51.709999084472656,
      "open": 53.099998474121094,
      "prevClose": 55.9900016784668,
      "volume": 1488759,
      "avgVolume20": 2619696,
      "avgDollarVolume20": 137822219,
      "liquid": true,
      "catalyst": true,
      "catalystHeadline": null,
      "breakout": false,
      "breakoutLevel": 69.38999938964844,
      "volumeSpike2x": false,
      "quoteTimestamp": "2026-07-17 00:00:00+02:00",
      "signal": "Hold",
      "dataSource": "Yahoo Finance / yfinance"
    },
    {
      "company": "Dassault Systemes SE",
      "ticker": "DSY.PA",
      "symbol": "DSY.PA",
      "column": "software",
      "currentPrice": 18.1299991607666,
      "change": -0.135,
      "percentChange": -0.7391,
      "high": 18.405000686645508,
      "low": 17.950000762939453,
      "open": 18.165000915527344,
      "prevClose": 18.264999389648438,
      "volume": 428238,
      "avgVolume20": 1895147,
      "avgDollarVolume20": 34359006,
      "liquid": true,
      "catalyst": true,
      "catalystHeadline": null,
      "breakout": false,
      "breakoutLevel": 18.670000076293945,
      "volumeSpike2x": false,
      "quoteTimestamp": "2026-07-17 00:00:00+02:00",
      "signal": "Hold",
      "dataSource": "Yahoo Finance / yfinance"
    },
    {
      "company": "Schneider Electric SE",
      "ticker": "SU.PA",
      "symbol": "SU.PA",
      "column": "industrial",
      "currentPrice": 259.75,
      "change": -4.6,
      "percentChange": -1.7401,
      "high": 260.3500061035156,
      "low": 257.1499938964844,
      "open": 258.54998779296875,
      "prevClose": 264.3500061035156,
      "volume": 306759,
      "avgVolume20": 876279,
      "avgDollarVolume20": 227613496,
      "liquid": true,
      "catalyst": true,
      "catalystHeadline": null,
      "breakout": false,
      "breakoutLevel": 292.75,
      "volumeSpike2x": false,
      "quoteTimestamp": "2026-07-17 00:00:00+02:00",
      "signal": "Hold",
      "dataSource": "Yahoo Finance / yfinance"
    },
    {
      "company": "Safran SA",
      "ticker": "SAF.PA",
      "symbol": "SAF.PA",
      "column": "aerospace",
      "currentPrice": 325.20001220703125,
      "change": -3.9,
      "percentChange": -1.185,
      "high": 327.3999938964844,
      "low": 323.79998779296875,
      "open": 325.20001220703125,
      "prevClose": 329.1000061035156,
      "volume": 124387,
      "avgVolume20": 685666,
      "avgDollarVolume20": 222978461,
      "liquid": true,
      "catalyst": true,
      "catalystHeadline": null,
      "breakout": false,
      "breakoutLevel": 357.1000061035156,
      "volumeSpike2x": false,
      "quoteTimestamp": "2026-07-17 00:00:00+02:00",
      "signal": "Hold",
      "dataSource": "Yahoo Finance / yfinance"
    },
    {
      "company": "Euronext N.V.",
      "ticker": "ENX.PA",
      "symbol": "ENX.PA",
      "column": "exchange",
      "currentPrice": 150.6999969482422,
      "change": -1.0,
      "percentChange": -0.6592,
      "high": 153.0,
      "low": 150.10000610351562,
      "open": 152.89999389648438,
      "prevClose": 151.6999969482422,
      "volume": 25436,
      "avgVolume20": 182171,
      "avgDollarVolume20": 27453101,
      "liquid": true,
      "catalyst": true,
      "catalystHeadline": null,
      "breakout": false,
      "breakoutLevel": 151.6999969482422,
      "volumeSpike2x": false,
      "quoteTimestamp": "2026-07-17 00:00:00+02:00",
      "signal": "Hold",
      "dataSource": "Yahoo Finance / yfinance"
    },
    {
      "company": "Rolls-Royce Holdings plc",
      "ticker": "RR.L",
      "symbol": "RR.L",
      "column": "aerospace",
      "currentPrice": 1356.199951171875,
      "change": -22.2001,
      "percentChange": -1.6106,
      "high": 1364.4000244140625,
      "low": 1347.5999755859375,
      "open": 1358.5999755859375,
      "prevClose": 1378.4000244140625,
      "volume": 3328754,
      "avgVolume20": 23514732,
      "avgDollarVolume20": 31890678594,
      "liquid": true,
      "catalyst": true,
      "catalystHeadline": null,
      "breakout": false,
      "breakoutLevel": 1504.199951171875,
      "volumeSpike2x": false,
      "quoteTimestamp": "2026-07-17 00:00:00+01:00",
      "signal": "Hold",
      "dataSource": "Yahoo Finance / yfinance"
    },
    {
      "company": "BAE Systems plc",
      "ticker": "BA.L",
      "symbol": "BA.L",
      "column": "defense",
      "currentPrice": 1862.0,
      "change": 28.0,
      "percentChange": 1.5267,
      "high": 1865.0,
      "low": 1817.0,
      "open": 1818.0,
      "prevClose": 1834.0,
      "volume": 906929,
      "avgVolume20": 7226019,
      "avgDollarVolume20": 13454848216,
      "liquid": true,
      "catalyst": true,
      "catalystHeadline": null,
      "breakout": false,
      "breakoutLevel": 2025.0,
      "volumeSpike2x": false,
      "quoteTimestamp": "2026-07-17 00:00:00+01:00",
      "signal": "Hold",
      "dataSource": "Yahoo Finance / yfinance"
    },
    {
      "company": "RELX PLC",
      "ticker": "REL.L",
      "symbol": "REL.L",
      "column": "information",
      "currentPrice": 2527.0,
      "change": 25.0,
      "percentChange": 0.9992,
      "high": 2663.0,
      "low": 2509.0,
      "open": 2517.0,
      "prevClose": 2502.0,
      "volume": 942984,
      "avgVolume20": 4255888,
      "avgDollarVolume20": 10754628344,
      "liquid": true,
      "catalyst": true,
      "catalystHeadline": null,
      "breakout": false,
      "breakoutLevel": 2502.0,
      "volumeSpike2x": false,
      "quoteTimestamp": "2026-07-17 00:00:00+01:00",
      "signal": "Hold",
      "dataSource": "Yahoo Finance / yfinance"
    },
    {
      "company": "ABB Ltd",
      "ticker": "ABBN.SW",
      "symbol": "ABBN.SW",
      "column": "industrial",
      "currentPrice": 77.72000122070312,
      "change": -0.54,
      "percentChange": -0.69,
      "high": 78.08000183105469,
      "low": 76.5,
      "open": 77.4000015258789,
      "prevClose": 78.26000213623047,
      "volume": 1642383,
      "avgVolume20": 2685978,
      "avgDollarVolume20": 208754229,
      "liquid": true,
      "catalyst": true,
      "catalystHeadline": null,
      "breakout": false,
      "breakoutLevel": 88.55999755859375,
      "volumeSpike2x": false,
      "quoteTimestamp": "2026-07-17 00:00:00+02:00",
      "signal": "Hold",
      "dataSource": "Yahoo Finance / yfinance"
    }
  ],
  "errors": []
}